{"kind":"Article","sha256":"88ab02916771a5e2dd71b4e760c0fe3810e72fc2b262e68fdfa27bdd3f009af9","slug":"intro-26","location":"/external/mechanics-BSc/book/stresses_displacements/displacements_frame/intro.md","dependencies":[],"frontmatter":{"title":"Solve displacements frame structures","content_includes_title":false,"authors":[{"nameParsed":{"literal":"Tom van Woudenberg","given":"Tom","non_dropping_particle":"van","family":"Woudenberg"},"name":"Tom van Woudenberg","id":"contributors-Users\\tomvanwoudenbe\\Git\\bridging_mechanics_myst\\book\\myst-generated-uid-0"}],"exports":[{"format":"md","filename":"intro.md","url":"/intro-21638312dfae3b04e9a53e03eb32ee15.md"}]},"mdast":{"type":"root","children":[{"type":"block","children":[{"type":"paragraph","position":{"start":{"line":5,"column":1},"end":{"line":5,"column":1}},"children":[{"type":"text","value":"This chapter includes the following topics:","position":{"start":{"line":5,"column":1},"end":{"line":5,"column":1}},"key":"rr8bIdMbWS"}],"key":"TUZ1zoBlUL"},{"type":"mystDirective","name":"tableofcontents","tight":"before","position":{"start":{"line":6,"column":1},"end":{"line":7,"column":1}},"key":"raFEOLzXKf"}],"key":"KeEpYfvTfy"}],"key":"UAetqs1fmP"},"references":{"cite":{"order":[],"data":{}}}}