{"kind":"Article","sha256":"ee2bc572b69b046a98e8a3c070c6d78a813aa5662eb9851e3701b53966ad64f0","slug":"intro-14","location":"/week_2/session_2/intro.md","dependencies":[],"frontmatter":{"title":"Lesson Wednesday September 11th","content_includes_title":false,"authors":[{"nameParsed":{"literal":"Tom van Woudenberg","given":"Tom","non_dropping_particle":"van","family":"Woudenberg"},"name":"Tom van Woudenberg","id":"contributors-Users\\tomvanwoudenbe\\Git\\bridging_mechanics_myst\\book\\myst-generated-uid-0"}],"thumbnail":"/structure-0b2a59caeaea2545662fe1a7cdb366da.svg","exports":[{"format":"md","filename":"intro.md","url":"/intro-ede872c4d20c3a220f35cf91c8645860.md"}]},"mdast":{"type":"root","children":[{"type":"block","children":[{"type":"paragraph","position":{"start":{"line":4,"column":1},"end":{"line":4,"column":1}},"children":[{"type":"text","value":"During today’s lesson you’ll work on a complex exercise on the topic of ‘Statics externally’. Please ask your questions regarding the ","position":{"start":{"line":4,"column":1},"end":{"line":4,"column":1}},"key":"qsozK5WayG"},{"type":"link","position":{"start":{"line":4,"column":1},"end":{"line":4,"column":1}},"children":[{"type":"text","value":"homework","position":{"start":{"line":4,"column":1},"end":{"line":4,"column":1}},"key":"WOsYyF1o2k"}],"identifier":"homework2.2","label":"homework2.2","url":"/intro-8","internal":true,"dataUrl":"/intro-8.json","key":"EIrEJkz56F"},{"type":"text","value":" as well!","position":{"start":{"line":4,"column":1},"end":{"line":4,"column":1}},"key":"yvvTDGEzb1"}],"key":"BoY1OoIq3e"},{"type":"heading","depth":2,"position":{"start":{"line":6,"column":1},"end":{"line":6,"column":1}},"children":[{"type":"text","value":"Exercise Statics externally","position":{"start":{"line":6,"column":1},"end":{"line":6,"column":1}},"key":"vdNhklKLRe"}],"identifier":"exercise-statics-externally","label":"Exercise Statics externally","html_id":"exercise-statics-externally","implicit":true,"key":"yDxRaRnyQE"},{"type":"paragraph","position":{"start":{"line":8,"column":1},"end":{"line":8,"column":1}},"children":[{"type":"text","value":"Given the following structure:","position":{"start":{"line":8,"column":1},"end":{"line":8,"column":1}},"key":"y5rN6edt1v"}],"key":"TtwB5kV8Pb"},{"type":"container","kind":"figure","children":[{"type":"image","url":"/structure-0b2a59caeaea2545662fe1a7cdb366da.svg","align":"center","key":"sH7NxrGupG","urlSource":"intro_data/structure.svg"}],"enumerator":"1","key":"ye9dshT64D"},{"type":"list","ordered":true,"start":1,"spread":false,"position":{"start":{"line":14,"column":1},"end":{"line":18,"column":1}},"children":[{"type":"listItem","spread":true,"position":{"start":{"line":14,"column":1},"end":{"line":14,"column":1}},"children":[{"type":"text","value":"Find the support reactions","position":{"start":{"line":14,"column":1},"end":{"line":14,"column":1}},"key":"yL2p4XMd8U"}],"key":"NkcyipVDVw"},{"type":"listItem","spread":true,"position":{"start":{"line":15,"column":1},"end":{"line":15,"column":1}},"children":[{"type":"text","value":"Find the bending moment, shear force and normal force just above ","position":{"start":{"line":15,"column":1},"end":{"line":15,"column":1}},"key":"V5K3hilkcn"},{"type":"inlineMath","value":"\\text{D}","position":{"start":{"line":15,"column":1},"end":{"line":15,"column":1}},"html":"<span class=\"katex\"><span class=\"katex-mathml\"><math xmlns=\"http://www.w3.org/1998/Math/MathML\"><semantics><mrow><mtext>D</mtext></mrow><annotation encoding=\"application/x-tex\">\\text{D}</annotation></semantics></math></span><span class=\"katex-html\" aria-hidden=\"true\"><span class=\"base\"><span class=\"strut\" style=\"height:0.6833em;\"></span><span class=\"mord text\"><span class=\"mord\">D</span></span></span></span></span>","key":"c5YYL5OkQl"}],"key":"yDnUams5ps"},{"type":"listItem","spread":true,"position":{"start":{"line":16,"column":1},"end":{"line":18,"column":1}},"children":[{"type":"text","value":"Find the bending moment, shear force and normal force just left of ","position":{"start":{"line":16,"column":1},"end":{"line":16,"column":1}},"key":"j845AqAUCF"},{"type":"inlineMath","value":"\\text{C}","position":{"start":{"line":16,"column":1},"end":{"line":16,"column":1}},"html":"<span class=\"katex\"><span class=\"katex-mathml\"><math xmlns=\"http://www.w3.org/1998/Math/MathML\"><semantics><mrow><mtext>C</mtext></mrow><annotation encoding=\"application/x-tex\">\\text{C}</annotation></semantics></math></span><span class=\"katex-html\" aria-hidden=\"true\"><span class=\"base\"><span class=\"strut\" style=\"height:0.6833em;\"></span><span class=\"mord text\"><span class=\"mord\">C</span></span></span></span></span>","key":"mD8TX0fhoA"}],"key":"zok6ysNdU2"}],"key":"LYaqWbFA1a"},{"type":"admonition","class":"tip, dropdown","children":[{"type":"admonitionTitle","children":[{"type":"text","value":"Solution assignment 1","position":{"start":{"line":19,"column":1},"end":{"line":19,"column":1}},"key":"lwMEBkRLWM"}],"key":"aPZOR7hZx6"},{"type":"container","kind":"figure","children":[{"type":"image","url":"/support_reactions-5c70438ee44dfcf6429fbb1cbaede7ff.svg","align":"center","key":"eFLoYNQpJY","urlSource":"intro_data/support_reactions.svg"}],"enumerator":"2","key":"EYgvbmShw3"}],"key":"S3FBbhROhz"},{"type":"admonition","class":"tip, dropdown","children":[{"type":"admonitionTitle","children":[{"type":"text","value":"Solution assignment 2","position":{"start":{"line":27,"column":1},"end":{"line":27,"column":1}},"key":"m1uxhCj0fJ"}],"key":"FpD8W3aMoC"},{"type":"list","ordered":false,"spread":false,"position":{"start":{"line":30,"column":1},"end":{"line":32,"column":1}},"children":[{"type":"listItem","spread":true,"position":{"start":{"line":30,"column":1},"end":{"line":30,"column":1}},"children":[{"type":"inlineMath","value":"M = 277 \\text{ kNm }","position":{"start":{"line":30,"column":1},"end":{"line":30,"column":1}},"html":"<span class=\"katex\"><span class=\"katex-mathml\"><math xmlns=\"http://www.w3.org/1998/Math/MathML\"><semantics><mrow><mi>M</mi><mo>=</mo><mn>277</mn><mtext> kNm </mtext></mrow><annotation encoding=\"application/x-tex\">M = 277 \\text{ kNm }</annotation></semantics></math></span><span class=\"katex-html\" aria-hidden=\"true\"><span class=\"base\"><span class=\"strut\" style=\"height:0.6833em;\"></span><span class=\"mord mathnormal\" style=\"margin-right:0.10903em;\">M</span><span class=\"mspace\" style=\"margin-right:0.2778em;\"></span><span class=\"mrel\">=</span><span class=\"mspace\" style=\"margin-right:0.2778em;\"></span></span><span class=\"base\"><span class=\"strut\" style=\"height:0.6944em;\"></span><span class=\"mord\">277</span><span class=\"mord text\"><span class=\"mord\"> kNm </span></span></span></span></span>","key":"LubI7X7f23"},{"type":"text","value":" ","position":{"start":{"line":30,"column":1},"end":{"line":30,"column":1}},"key":"Iiz4UbTaCf"},{"type":"image","url":"/MD-c0c7c60ae53f5f688710278a5352b16d.svg","position":{"start":{"line":30,"column":1},"end":{"line":30,"column":1}},"key":"l2awgYccBd","urlSource":"intro_data/MD.svg"}],"key":"Q1BDq2EznQ"},{"type":"listItem","spread":true,"position":{"start":{"line":31,"column":1},"end":{"line":31,"column":1}},"children":[{"type":"inlineMath","value":"V = 28 \\text{ kN }","position":{"start":{"line":31,"column":1},"end":{"line":31,"column":1}},"html":"<span class=\"katex\"><span class=\"katex-mathml\"><math xmlns=\"http://www.w3.org/1998/Math/MathML\"><semantics><mrow><mi>V</mi><mo>=</mo><mn>28</mn><mtext> kN </mtext></mrow><annotation encoding=\"application/x-tex\">V = 28 \\text{ kN }</annotation></semantics></math></span><span class=\"katex-html\" aria-hidden=\"true\"><span class=\"base\"><span class=\"strut\" style=\"height:0.6833em;\"></span><span class=\"mord mathnormal\" style=\"margin-right:0.22222em;\">V</span><span class=\"mspace\" style=\"margin-right:0.2778em;\"></span><span class=\"mrel\">=</span><span class=\"mspace\" style=\"margin-right:0.2778em;\"></span></span><span class=\"base\"><span class=\"strut\" style=\"height:0.6944em;\"></span><span class=\"mord\">28</span><span class=\"mord text\"><span class=\"mord\"> kN </span></span></span></span></span>","key":"wIGxC6um5N"},{"type":"text","value":" ","position":{"start":{"line":31,"column":1},"end":{"line":31,"column":1}},"key":"Hdrtlp7cFB"},{"type":"image","url":"/VD-cb31437dc01860500ecb91e173b9af6c.svg","position":{"start":{"line":31,"column":1},"end":{"line":31,"column":1}},"key":"nk9puLDb61","urlSource":"intro_data/VD.svg"}],"key":"pYBUtHS0Qf"},{"type":"listItem","spread":true,"position":{"start":{"line":32,"column":1},"end":{"line":32,"column":1}},"children":[{"type":"inlineMath","value":"N = -199 \\text{ kN }","position":{"start":{"line":32,"column":1},"end":{"line":32,"column":1}},"html":"<span class=\"katex\"><span class=\"katex-mathml\"><math xmlns=\"http://www.w3.org/1998/Math/MathML\"><semantics><mrow><mi>N</mi><mo>=</mo><mo>−</mo><mn>199</mn><mtext> kN </mtext></mrow><annotation encoding=\"application/x-tex\">N = -199 \\text{ kN }</annotation></semantics></math></span><span class=\"katex-html\" aria-hidden=\"true\"><span class=\"base\"><span class=\"strut\" style=\"height:0.6833em;\"></span><span class=\"mord mathnormal\" style=\"margin-right:0.10903em;\">N</span><span class=\"mspace\" style=\"margin-right:0.2778em;\"></span><span class=\"mrel\">=</span><span class=\"mspace\" style=\"margin-right:0.2778em;\"></span></span><span class=\"base\"><span class=\"strut\" style=\"height:0.7778em;vertical-align:-0.0833em;\"></span><span class=\"mord\">−</span><span class=\"mord\">199</span><span class=\"mord text\"><span class=\"mord\"> kN </span></span></span></span></span>","key":"bLiwBoDN5Q"}],"key":"GlTJK9OfLr"}],"key":"KQMrArQ5H7"}],"key":"z6zLWAbJQ7"},{"type":"admonition","class":"tip, dropdown","children":[{"type":"admonitionTitle","children":[{"type":"text","value":"Solution assignment 3","position":{"start":{"line":36,"column":1},"end":{"line":36,"column":1}},"key":"zutDhBSJbi"}],"key":"lk3AOW46En"},{"type":"list","ordered":false,"spread":false,"position":{"start":{"line":39,"column":1},"end":{"line":41,"column":1}},"children":[{"type":"listItem","spread":true,"position":{"start":{"line":39,"column":1},"end":{"line":39,"column":1}},"children":[{"type":"inlineMath","value":"M = 0 \\text{ kNm }","position":{"start":{"line":39,"column":1},"end":{"line":39,"column":1}},"html":"<span class=\"katex\"><span class=\"katex-mathml\"><math xmlns=\"http://www.w3.org/1998/Math/MathML\"><semantics><mrow><mi>M</mi><mo>=</mo><mn>0</mn><mtext> kNm </mtext></mrow><annotation encoding=\"application/x-tex\">M = 0 \\text{ kNm }</annotation></semantics></math></span><span class=\"katex-html\" aria-hidden=\"true\"><span class=\"base\"><span class=\"strut\" style=\"height:0.6833em;\"></span><span class=\"mord mathnormal\" style=\"margin-right:0.10903em;\">M</span><span class=\"mspace\" style=\"margin-right:0.2778em;\"></span><span class=\"mrel\">=</span><span class=\"mspace\" style=\"margin-right:0.2778em;\"></span></span><span class=\"base\"><span class=\"strut\" style=\"height:0.6944em;\"></span><span class=\"mord\">0</span><span class=\"mord text\"><span class=\"mord\"> kNm </span></span></span></span></span>","key":"PildBSBc01"}],"key":"vE0nccdI8m"},{"type":"listItem","spread":true,"position":{"start":{"line":40,"column":1},"end":{"line":40,"column":1}},"children":[{"type":"inlineMath","value":"V = 110 \\text{ kN }","position":{"start":{"line":40,"column":1},"end":{"line":40,"column":1}},"html":"<span class=\"katex\"><span class=\"katex-mathml\"><math xmlns=\"http://www.w3.org/1998/Math/MathML\"><semantics><mrow><mi>V</mi><mo>=</mo><mn>110</mn><mtext> kN </mtext></mrow><annotation encoding=\"application/x-tex\">V = 110 \\text{ kN }</annotation></semantics></math></span><span class=\"katex-html\" aria-hidden=\"true\"><span class=\"base\"><span class=\"strut\" style=\"height:0.6833em;\"></span><span class=\"mord mathnormal\" style=\"margin-right:0.22222em;\">V</span><span class=\"mspace\" style=\"margin-right:0.2778em;\"></span><span class=\"mrel\">=</span><span class=\"mspace\" style=\"margin-right:0.2778em;\"></span></span><span class=\"base\"><span class=\"strut\" style=\"height:0.6944em;\"></span><span class=\"mord\">110</span><span class=\"mord text\"><span class=\"mord\"> kN </span></span></span></span></span>","key":"bqryssMyGW"},{"type":"text","value":" ","position":{"start":{"line":40,"column":1},"end":{"line":40,"column":1}},"key":"AZUVcbJY7L"},{"type":"image","url":"/VC-fa78f14e4fd899b1dc2cad0b96331ae1.svg","position":{"start":{"line":40,"column":1},"end":{"line":40,"column":1}},"key":"sWVy263hdx","urlSource":"intro_data/VC.svg"}],"key":"NtybrqOj7Y"},{"type":"listItem","spread":true,"position":{"start":{"line":41,"column":1},"end":{"line":41,"column":1}},"children":[{"type":"inlineMath","value":"N = +61 \\text{ kN }","position":{"start":{"line":41,"column":1},"end":{"line":41,"column":1}},"html":"<span class=\"katex\"><span class=\"katex-mathml\"><math xmlns=\"http://www.w3.org/1998/Math/MathML\"><semantics><mrow><mi>N</mi><mo>=</mo><mo>+</mo><mn>61</mn><mtext> kN </mtext></mrow><annotation encoding=\"application/x-tex\">N = +61 \\text{ kN }</annotation></semantics></math></span><span class=\"katex-html\" aria-hidden=\"true\"><span class=\"base\"><span class=\"strut\" style=\"height:0.6833em;\"></span><span class=\"mord mathnormal\" style=\"margin-right:0.10903em;\">N</span><span class=\"mspace\" style=\"margin-right:0.2778em;\"></span><span class=\"mrel\">=</span><span class=\"mspace\" style=\"margin-right:0.2778em;\"></span></span><span class=\"base\"><span class=\"strut\" style=\"height:0.7778em;vertical-align:-0.0833em;\"></span><span class=\"mord\">+</span><span class=\"mord\">61</span><span class=\"mord text\"><span class=\"mord\"> kN </span></span></span></span></span>","key":"BgIHDBNUYW"}],"key":"A69HJYOvje"}],"key":"eEJzEGgFIU"}],"key":"fZEr8m7p2N"}],"key":"rL5dlx7Puj"}],"key":"gJEx8NwlVp"},"references":{"cite":{"order":[],"data":{}}}}