{"kind":"Article","sha256":"87d2d1bbca6f1c2a30c6a2326fc9aed71ffa176127fb11aea746b28de0b7a8e0","slug":"shear","location":"/external/mechanics-BSc/book/stresses_displacements/solve_bending/shear.md","dependencies":[],"frontmatter":{"title":"Shear stresses","content_includes_title":false,"authors":[{"nameParsed":{"literal":"Tom van Woudenberg","given":"Tom","non_dropping_particle":"van","family":"Woudenberg"},"name":"Tom van Woudenberg","id":"contributors-Users\\tomvanwoudenbe\\Git\\bridging_mechanics_myst\\book\\myst-generated-uid-0"}],"thumbnail":"/image_shear-5bed7e2ef97d26a39bfff505ec4c6e51.png","exports":[{"format":"md","filename":"shear.md","url":"/shear-2eb7245ac0a7afddd6dba99403ab0733.md"}]},"mdast":{"type":"root","children":[{"type":"block","children":[{"type":"container","kind":"figure","children":[{"type":"image","url":"/image_shear-5bed7e2ef97d26a39bfff505ec4c6e51.png","alt":"Figure 5.13b,c,d ","width":"600","align":"center","data":{"altTextIsAutoGenerated":true},"key":"jpGqrejqpR","urlSource":"./shear_data/image_shear.png"},{"type":"caption","children":[{"type":"paragraph","position":{"start":{"line":12,"column":1},"end":{"line":12,"column":1}},"children":[{"type":"text","value":"Figure 5.13b,c,d ","position":{"start":{"line":12,"column":1},"end":{"line":12,"column":1}},"key":"hv5wcZQiI6"},{"type":"citeGroup","kind":"narrative","children":[{"type":"cite","kind":"narrative","label":"Hartsuijker2007","identifier":"hartsuijker2007","children":[{"type":"text","value":"Hartsuijker & Welleman (2007)","key":"dQS6zCYPM5"}],"enumerator":"1","key":"Ixslly83Ev"}],"key":"dqEPpLSy74"}],"key":"t5JTsvwYJg"}],"key":"QMis6lOZJz"}],"enumerator":"1","key":"LFAcejskaC"},{"type":"heading","depth":2,"position":{"start":{"line":14,"column":1},"end":{"line":14,"column":1}},"children":[{"type":"text","value":"Longitudinal shear stresses","position":{"start":{"line":14,"column":1},"end":{"line":14,"column":1}},"key":"y50evJS53w"}],"identifier":"longitudinal-shear-stresses","label":"Longitudinal shear stresses","html_id":"longitudinal-shear-stresses","implicit":true,"key":"ojYMUHMlwZ"},{"type":"paragraph","position":{"start":{"line":16,"column":1},"end":{"line":16,"column":1}},"children":[{"type":"text","value":"The shear force per unit length in the longitudinal direction is given by:","position":{"start":{"line":16,"column":1},"end":{"line":16,"column":1}},"key":"CTuGE02MDd"}],"key":"vKiedB1SvA"},{"type":"math","value":"s_x^a = -\\cfrac{dM_z}{dx} \\cfrac{S_z^a}{I_{zz}} = -\\cfrac{V_zS_z^a}{I_{zz}}","position":{"start":{"line":18,"column":1},"end":{"line":18,"column":1}},"html":"<span class=\"katex-display\"><span class=\"katex\"><span class=\"katex-mathml\"><math xmlns=\"http://www.w3.org/1998/Math/MathML\" display=\"block\"><semantics><mrow><msubsup><mi>s</mi><mi>x</mi><mi>a</mi></msubsup><mo>=</mo><mo>−</mo><mfrac><mrow><mi>d</mi><msub><mi>M</mi><mi>z</mi></msub></mrow><mrow><mi>d</mi><mi>x</mi></mrow></mfrac><mfrac><msubsup><mi>S</mi><mi>z</mi><mi>a</mi></msubsup><msub><mi>I</mi><mrow><mi>z</mi><mi>z</mi></mrow></msub></mfrac><mo>=</mo><mo>−</mo><mfrac><mrow><msub><mi>V</mi><mi>z</mi></msub><msubsup><mi>S</mi><mi>z</mi><mi>a</mi></msubsup></mrow><msub><mi>I</mi><mrow><mi>z</mi><mi>z</mi></mrow></msub></mfrac></mrow><annotation encoding=\"application/x-tex\">s_x^a = -\\cfrac{dM_z}{dx} \\cfrac{S_z^a}{I_{zz}} = -\\cfrac{V_zS_z^a}{I_{zz}}</annotation></semantics></math></span><span class=\"katex-html\" aria-hidden=\"true\"><span class=\"base\"><span class=\"strut\" style=\"height:0.9614em;vertical-align:-0.247em;\"></span><span class=\"mord\"><span class=\"mord mathnormal\">s</span><span class=\"msupsub\"><span class=\"vlist-t vlist-t2\"><span class=\"vlist-r\"><span class=\"vlist\" style=\"height:0.7144em;\"><span style=\"top:-2.453em;margin-left:0em;margin-right:0.05em;\"><span class=\"pstrut\" style=\"height:2.7em;\"></span><span class=\"sizing reset-size6 size3 mtight\"><span class=\"mord mathnormal mtight\">x</span></span></span><span style=\"top:-3.113em;margin-right:0.05em;\"><span class=\"pstrut\" style=\"height:2.7em;\"></span><span class=\"sizing reset-size6 size3 mtight\"><span class=\"mord mathnormal mtight\">a</span></span></span></span><span class=\"vlist-s\">​</span></span><span class=\"vlist-r\"><span class=\"vlist\" style=\"height:0.247em;\"><span></span></span></span></span></span></span><span class=\"mspace\" style=\"margin-right:0.2778em;\"></span><span class=\"mrel\">=</span><span class=\"mspace\" style=\"margin-right:0.2778em;\"></span></span><span class=\"base\"><span class=\"strut\" style=\"height:2.426em;vertical-align:-0.836em;\"></span><span class=\"mord\">−</span><span class=\"mord\"><span class=\"mopen nulldelimiter\"></span><span class=\"mfrac\"><span class=\"vlist-t vlist-t2\"><span class=\"vlist-r\"><span class=\"vlist\" style=\"height:1.59em;\"><span style=\"top:-2.314em;\"><span class=\"pstrut\" style=\"height:3em;\"></span><span class=\"mord\"><span class=\"mord mathnormal\">d</span><span class=\"mord mathnormal\">x</span></span></span><span style=\"top:-3.23em;\"><span class=\"pstrut\" style=\"height:3em;\"></span><span class=\"frac-line\" style=\"border-bottom-width:0.04em;\"></span></span><span style=\"top:-3.74em;\"><span class=\"pstrut\" style=\"height:3em;\"></span><span class=\"mord\"><span class=\"mord mathnormal\">d</span><span class=\"mord\"><span class=\"mord mathnormal\" style=\"margin-right:0.10903em;\">M</span><span class=\"msupsub\"><span class=\"vlist-t vlist-t2\"><span class=\"vlist-r\"><span class=\"vlist\" style=\"height:0.1514em;\"><span style=\"top:-2.55em;margin-left:-0.109em;margin-right:0.05em;\"><span class=\"pstrut\" style=\"height:2.7em;\"></span><span class=\"sizing reset-size6 size3 mtight\"><span class=\"mord mathnormal mtight\" style=\"margin-right:0.04398em;\">z</span></span></span></span><span class=\"vlist-s\">​</span></span><span class=\"vlist-r\"><span class=\"vlist\" style=\"height:0.15em;\"><span></span></span></span></span></span></span></span></span></span><span class=\"vlist-s\">​</span></span><span class=\"vlist-r\"><span class=\"vlist\" style=\"height:0.686em;\"><span></span></span></span></span></span><span></span></span><span class=\"mord\"><span class=\"mopen nulldelimiter\"></span><span class=\"mfrac\"><span class=\"vlist-t vlist-t2\"><span class=\"vlist-r\"><span class=\"vlist\" style=\"height:1.59em;\"><span style=\"top:-2.314em;\"><span class=\"pstrut\" style=\"height:3em;\"></span><span class=\"mord\"><span class=\"mord\"><span class=\"mord mathnormal\" style=\"margin-right:0.07847em;\">I</span><span class=\"msupsub\"><span class=\"vlist-t vlist-t2\"><span class=\"vlist-r\"><span class=\"vlist\" style=\"height:0.1514em;\"><span style=\"top:-2.55em;margin-left:-0.0785em;margin-right:0.05em;\"><span class=\"pstrut\" style=\"height:2.7em;\"></span><span class=\"sizing reset-size6 size3 mtight\"><span class=\"mord mtight\"><span class=\"mord mathnormal mtight\" style=\"margin-right:0.04398em;\">zz</span></span></span></span></span><span class=\"vlist-s\">​</span></span><span class=\"vlist-r\"><span class=\"vlist\" style=\"height:0.15em;\"><span></span></span></span></span></span></span></span></span><span style=\"top:-3.23em;\"><span class=\"pstrut\" style=\"height:3em;\"></span><span class=\"frac-line\" style=\"border-bottom-width:0.04em;\"></span></span><span style=\"top:-3.74em;\"><span class=\"pstrut\" style=\"height:3em;\"></span><span class=\"mord\"><span class=\"mord\"><span class=\"mord mathnormal\" style=\"margin-right:0.05764em;\">S</span><span class=\"msupsub\"><span class=\"vlist-t vlist-t2\"><span class=\"vlist-r\"><span class=\"vlist\" style=\"height:0.6644em;\"><span style=\"top:-2.453em;margin-left:-0.0576em;margin-right:0.05em;\"><span class=\"pstrut\" style=\"height:2.7em;\"></span><span class=\"sizing reset-size6 size3 mtight\"><span class=\"mord mathnormal mtight\" style=\"margin-right:0.04398em;\">z</span></span></span><span style=\"top:-3.063em;margin-right:0.05em;\"><span class=\"pstrut\" style=\"height:2.7em;\"></span><span class=\"sizing reset-size6 size3 mtight\"><span class=\"mord mathnormal mtight\">a</span></span></span></span><span class=\"vlist-s\">​</span></span><span class=\"vlist-r\"><span class=\"vlist\" style=\"height:0.247em;\"><span></span></span></span></span></span></span></span></span></span><span class=\"vlist-s\">​</span></span><span class=\"vlist-r\"><span class=\"vlist\" style=\"height:0.836em;\"><span></span></span></span></span></span><span></span></span><span class=\"mspace\" style=\"margin-right:0.2778em;\"></span><span class=\"mrel\">=</span><span class=\"mspace\" style=\"margin-right:0.2778em;\"></span></span><span class=\"base\"><span class=\"strut\" style=\"height:2.426em;vertical-align:-0.836em;\"></span><span class=\"mord\">−</span><span class=\"mord\"><span class=\"mopen nulldelimiter\"></span><span class=\"mfrac\"><span class=\"vlist-t vlist-t2\"><span class=\"vlist-r\"><span class=\"vlist\" style=\"height:1.59em;\"><span style=\"top:-2.314em;\"><span class=\"pstrut\" style=\"height:3em;\"></span><span class=\"mord\"><span class=\"mord\"><span class=\"mord mathnormal\" style=\"margin-right:0.07847em;\">I</span><span class=\"msupsub\"><span class=\"vlist-t vlist-t2\"><span class=\"vlist-r\"><span class=\"vlist\" style=\"height:0.1514em;\"><span style=\"top:-2.55em;margin-left:-0.0785em;margin-right:0.05em;\"><span class=\"pstrut\" style=\"height:2.7em;\"></span><span class=\"sizing reset-size6 size3 mtight\"><span class=\"mord mtight\"><span class=\"mord mathnormal mtight\" style=\"margin-right:0.04398em;\">zz</span></span></span></span></span><span class=\"vlist-s\">​</span></span><span class=\"vlist-r\"><span class=\"vlist\" style=\"height:0.15em;\"><span></span></span></span></span></span></span></span></span><span style=\"top:-3.23em;\"><span class=\"pstrut\" style=\"height:3em;\"></span><span class=\"frac-line\" style=\"border-bottom-width:0.04em;\"></span></span><span style=\"top:-3.74em;\"><span class=\"pstrut\" style=\"height:3em;\"></span><span class=\"mord\"><span class=\"mord\"><span class=\"mord mathnormal\" style=\"margin-right:0.22222em;\">V</span><span class=\"msupsub\"><span class=\"vlist-t vlist-t2\"><span class=\"vlist-r\"><span class=\"vlist\" style=\"height:0.1514em;\"><span style=\"top:-2.55em;margin-left:-0.2222em;margin-right:0.05em;\"><span class=\"pstrut\" style=\"height:2.7em;\"></span><span class=\"sizing reset-size6 size3 mtight\"><span class=\"mord mathnormal mtight\" style=\"margin-right:0.04398em;\">z</span></span></span></span><span class=\"vlist-s\">​</span></span><span class=\"vlist-r\"><span class=\"vlist\" style=\"height:0.15em;\"><span></span></span></span></span></span></span><span class=\"mord\"><span class=\"mord mathnormal\" style=\"margin-right:0.05764em;\">S</span><span class=\"msupsub\"><span class=\"vlist-t vlist-t2\"><span class=\"vlist-r\"><span class=\"vlist\" style=\"height:0.6644em;\"><span style=\"top:-2.453em;margin-left:-0.0576em;margin-right:0.05em;\"><span class=\"pstrut\" style=\"height:2.7em;\"></span><span class=\"sizing reset-size6 size3 mtight\"><span class=\"mord mathnormal mtight\" style=\"margin-right:0.04398em;\">z</span></span></span><span style=\"top:-3.063em;margin-right:0.05em;\"><span class=\"pstrut\" style=\"height:2.7em;\"></span><span class=\"sizing reset-size6 size3 mtight\"><span class=\"mord mathnormal mtight\">a</span></span></span></span><span class=\"vlist-s\">​</span></span><span class=\"vlist-r\"><span class=\"vlist\" style=\"height:0.247em;\"><span></span></span></span></span></span></span></span></span></span><span class=\"vlist-s\">​</span></span><span class=\"vlist-r\"><span class=\"vlist\" style=\"height:0.836em;\"><span></span></span></span></span></span><span></span></span></span></span></span></span>","enumerator":"1","key":"R0BAaIHjDi"},{"type":"paragraph","position":{"start":{"line":20,"column":1},"end":{"line":20,"column":1}},"children":[{"type":"text","value":"or alternatively:","position":{"start":{"line":20,"column":1},"end":{"line":20,"column":1}},"key":"BpYhVlQxZK"}],"key":"znsJFriLlM"},{"type":"math","value":"s_x^a =  - {V_z}\\cfrac{{{N^a}\\left( {{\\text{due to }}M_z^*} \\right)}}{{M_z^*}}","position":{"start":{"line":22,"column":1},"end":{"line":22,"column":1}},"html":"<span class=\"katex-display\"><span class=\"katex\"><span class=\"katex-mathml\"><math xmlns=\"http://www.w3.org/1998/Math/MathML\" display=\"block\"><semantics><mrow><msubsup><mi>s</mi><mi>x</mi><mi>a</mi></msubsup><mo>=</mo><mo>−</mo><msub><mi>V</mi><mi>z</mi></msub><mfrac><mrow><msup><mi>N</mi><mi>a</mi></msup><mrow><mo fence=\"true\">(</mo><mrow><mtext>due to </mtext><msubsup><mi>M</mi><mi>z</mi><mo>∗</mo></msubsup></mrow><mo fence=\"true\">)</mo></mrow></mrow><msubsup><mi>M</mi><mi>z</mi><mo>∗</mo></msubsup></mfrac></mrow><annotation encoding=\"application/x-tex\">s_x^a =  - {V_z}\\cfrac{{{N^a}\\left( {{\\text{due to }}M_z^*} \\right)}}{{M_z^*}}</annotation></semantics></math></span><span class=\"katex-html\" aria-hidden=\"true\"><span class=\"base\"><span class=\"strut\" style=\"height:0.9614em;vertical-align:-0.247em;\"></span><span class=\"mord\"><span class=\"mord mathnormal\">s</span><span class=\"msupsub\"><span class=\"vlist-t vlist-t2\"><span class=\"vlist-r\"><span class=\"vlist\" style=\"height:0.7144em;\"><span style=\"top:-2.453em;margin-left:0em;margin-right:0.05em;\"><span class=\"pstrut\" style=\"height:2.7em;\"></span><span class=\"sizing reset-size6 size3 mtight\"><span class=\"mord mathnormal mtight\">x</span></span></span><span style=\"top:-3.113em;margin-right:0.05em;\"><span class=\"pstrut\" style=\"height:2.7em;\"></span><span class=\"sizing reset-size6 size3 mtight\"><span class=\"mord mathnormal mtight\">a</span></span></span></span><span class=\"vlist-s\">​</span></span><span class=\"vlist-r\"><span class=\"vlist\" style=\"height:0.247em;\"><span></span></span></span></span></span></span><span class=\"mspace\" style=\"margin-right:0.2778em;\"></span><span class=\"mrel\">=</span><span class=\"mspace\" style=\"margin-right:0.2778em;\"></span></span><span class=\"base\"><span class=\"strut\" style=\"height:2.523em;vertical-align:-0.933em;\"></span><span class=\"mord\">−</span><span class=\"mord\"><span class=\"mord\"><span class=\"mord mathnormal\" style=\"margin-right:0.22222em;\">V</span><span class=\"msupsub\"><span class=\"vlist-t vlist-t2\"><span class=\"vlist-r\"><span class=\"vlist\" style=\"height:0.1514em;\"><span style=\"top:-2.55em;margin-left:-0.2222em;margin-right:0.05em;\"><span class=\"pstrut\" style=\"height:2.7em;\"></span><span class=\"sizing reset-size6 size3 mtight\"><span class=\"mord mathnormal mtight\" style=\"margin-right:0.04398em;\">z</span></span></span></span><span class=\"vlist-s\">​</span></span><span class=\"vlist-r\"><span class=\"vlist\" style=\"height:0.15em;\"><span></span></span></span></span></span></span></span><span class=\"mord\"><span class=\"mopen nulldelimiter\"></span><span class=\"mfrac\"><span class=\"vlist-t vlist-t2\"><span class=\"vlist-r\"><span class=\"vlist\" style=\"height:1.59em;\"><span style=\"top:-2.314em;\"><span class=\"pstrut\" style=\"height:3em;\"></span><span class=\"mord\"><span class=\"mord\"><span class=\"mord\"><span class=\"mord mathnormal\" style=\"margin-right:0.10903em;\">M</span><span class=\"msupsub\"><span class=\"vlist-t vlist-t2\"><span class=\"vlist-r\"><span class=\"vlist\" style=\"height:0.6147em;\"><span style=\"top:-2.453em;margin-left:-0.109em;margin-right:0.05em;\"><span class=\"pstrut\" style=\"height:2.7em;\"></span><span class=\"sizing reset-size6 size3 mtight\"><span class=\"mord mathnormal mtight\" style=\"margin-right:0.04398em;\">z</span></span></span><span style=\"top:-2.989em;margin-right:0.05em;\"><span class=\"pstrut\" style=\"height:2.7em;\"></span><span class=\"sizing reset-size6 size3 mtight\"><span class=\"mbin mtight\">∗</span></span></span></span><span class=\"vlist-s\">​</span></span><span class=\"vlist-r\"><span class=\"vlist\" style=\"height:0.247em;\"><span></span></span></span></span></span></span></span></span></span><span style=\"top:-3.23em;\"><span class=\"pstrut\" style=\"height:3em;\"></span><span class=\"frac-line\" style=\"border-bottom-width:0.04em;\"></span></span><span style=\"top:-3.74em;\"><span class=\"pstrut\" style=\"height:3em;\"></span><span class=\"mord\"><span class=\"mord\"><span class=\"mord\"><span class=\"mord\"><span class=\"mord mathnormal\" style=\"margin-right:0.10903em;\">N</span><span class=\"msupsub\"><span class=\"vlist-t\"><span class=\"vlist-r\"><span class=\"vlist\" style=\"height:0.6644em;\"><span style=\"top:-3.063em;margin-right:0.05em;\"><span class=\"pstrut\" style=\"height:2.7em;\"></span><span class=\"sizing reset-size6 size3 mtight\"><span class=\"mord mathnormal mtight\">a</span></span></span></span></span></span></span></span></span><span class=\"mspace\" style=\"margin-right:0.1667em;\"></span><span class=\"minner\"><span class=\"mopen delimcenter\" style=\"top:0em;\">(</span><span class=\"mord\"><span class=\"mord\"><span class=\"mord text\"><span class=\"mord\">due to </span></span></span><span class=\"mord\"><span class=\"mord mathnormal\" style=\"margin-right:0.10903em;\">M</span><span class=\"msupsub\"><span class=\"vlist-t vlist-t2\"><span class=\"vlist-r\"><span class=\"vlist\" style=\"height:0.6887em;\"><span style=\"top:-2.453em;margin-left:-0.109em;margin-right:0.05em;\"><span class=\"pstrut\" style=\"height:2.7em;\"></span><span class=\"sizing reset-size6 size3 mtight\"><span class=\"mord mathnormal mtight\" style=\"margin-right:0.04398em;\">z</span></span></span><span style=\"top:-3.063em;margin-right:0.05em;\"><span class=\"pstrut\" style=\"height:2.7em;\"></span><span class=\"sizing reset-size6 size3 mtight\"><span class=\"mbin mtight\">∗</span></span></span></span><span class=\"vlist-s\">​</span></span><span class=\"vlist-r\"><span class=\"vlist\" style=\"height:0.247em;\"><span></span></span></span></span></span></span></span><span class=\"mclose delimcenter\" style=\"top:0em;\">)</span></span></span></span></span></span><span class=\"vlist-s\">​</span></span><span class=\"vlist-r\"><span class=\"vlist\" style=\"height:0.933em;\"><span></span></span></span></span></span><span></span></span></span></span></span></span>","enumerator":"2","key":"s34SkfSzUS"},{"type":"paragraph","position":{"start":{"line":24,"column":1},"end":{"line":24,"column":1}},"children":[{"type":"text","value":"The shear stress is given by:","position":{"start":{"line":24,"column":1},"end":{"line":24,"column":1}},"key":"RYlbFgp3EW"}],"key":"PBqMjxpS2U"},{"type":"math","value":"\\sigma_{mx} = \\frac{s_x^a}{b^a}","position":{"start":{"line":26,"column":1},"end":{"line":26,"column":1}},"html":"<span class=\"katex-display\"><span class=\"katex\"><span class=\"katex-mathml\"><math xmlns=\"http://www.w3.org/1998/Math/MathML\" display=\"block\"><semantics><mrow><msub><mi>σ</mi><mrow><mi>m</mi><mi>x</mi></mrow></msub><mo>=</mo><mfrac><msubsup><mi>s</mi><mi>x</mi><mi>a</mi></msubsup><msup><mi>b</mi><mi>a</mi></msup></mfrac></mrow><annotation encoding=\"application/x-tex\">\\sigma_{mx} = \\frac{s_x^a}{b^a}</annotation></semantics></math></span><span class=\"katex-html\" aria-hidden=\"true\"><span class=\"base\"><span class=\"strut\" style=\"height:0.5806em;vertical-align:-0.15em;\"></span><span class=\"mord\"><span class=\"mord mathnormal\" style=\"margin-right:0.03588em;\">σ</span><span class=\"msupsub\"><span class=\"vlist-t vlist-t2\"><span class=\"vlist-r\"><span class=\"vlist\" style=\"height:0.1514em;\"><span style=\"top:-2.55em;margin-left:-0.0359em;margin-right:0.05em;\"><span class=\"pstrut\" style=\"height:2.7em;\"></span><span class=\"sizing reset-size6 size3 mtight\"><span class=\"mord mtight\"><span class=\"mord mathnormal mtight\">m</span><span class=\"mord mathnormal mtight\">x</span></span></span></span></span><span class=\"vlist-s\">​</span></span><span class=\"vlist-r\"><span class=\"vlist\" style=\"height:0.15em;\"><span></span></span></span></span></span></span><span class=\"mspace\" style=\"margin-right:0.2778em;\"></span><span class=\"mrel\">=</span><span class=\"mspace\" style=\"margin-right:0.2778em;\"></span></span><span class=\"base\"><span class=\"strut\" style=\"height:2.0274em;vertical-align:-0.686em;\"></span><span class=\"mord\"><span class=\"mopen nulldelimiter\"></span><span class=\"mfrac\"><span class=\"vlist-t vlist-t2\"><span class=\"vlist-r\"><span class=\"vlist\" style=\"height:1.3414em;\"><span style=\"top:-2.314em;\"><span class=\"pstrut\" style=\"height:3em;\"></span><span class=\"mord\"><span class=\"mord\"><span class=\"mord mathnormal\">b</span><span class=\"msupsub\"><span class=\"vlist-t\"><span class=\"vlist-r\"><span class=\"vlist\" style=\"height:0.5904em;\"><span style=\"top:-2.989em;margin-right:0.05em;\"><span class=\"pstrut\" style=\"height:2.7em;\"></span><span class=\"sizing reset-size6 size3 mtight\"><span class=\"mord mathnormal mtight\">a</span></span></span></span></span></span></span></span></span></span><span style=\"top:-3.23em;\"><span class=\"pstrut\" style=\"height:3em;\"></span><span class=\"frac-line\" style=\"border-bottom-width:0.04em;\"></span></span><span style=\"top:-3.677em;\"><span class=\"pstrut\" style=\"height:3em;\"></span><span class=\"mord\"><span class=\"mord\"><span class=\"mord mathnormal\">s</span><span class=\"msupsub\"><span class=\"vlist-t vlist-t2\"><span class=\"vlist-r\"><span class=\"vlist\" style=\"height:0.6644em;\"><span style=\"top:-2.453em;margin-left:0em;margin-right:0.05em;\"><span class=\"pstrut\" style=\"height:2.7em;\"></span><span class=\"sizing reset-size6 size3 mtight\"><span class=\"mord mathnormal mtight\">x</span></span></span><span style=\"top:-3.063em;margin-right:0.05em;\"><span class=\"pstrut\" style=\"height:2.7em;\"></span><span class=\"sizing reset-size6 size3 mtight\"><span class=\"mord mathnormal mtight\">a</span></span></span></span><span class=\"vlist-s\">​</span></span><span class=\"vlist-r\"><span class=\"vlist\" style=\"height:0.247em;\"><span></span></span></span></span></span></span></span></span></span><span class=\"vlist-s\">​</span></span><span class=\"vlist-r\"><span class=\"vlist\" style=\"height:0.686em;\"><span></span></span></span></span></span><span class=\"mclose nulldelimiter\"></span></span></span></span></span></span>","enumerator":"3","key":"EieIFoPIis"},{"type":"paragraph","position":{"start":{"line":28,"column":1},"end":{"line":28,"column":1}},"children":[{"type":"text","value":"This is treated in chapter 5.1 and 5.2 of the book Engineering Mechanics Volume 2 ","position":{"start":{"line":28,"column":1},"end":{"line":28,"column":1}},"key":"hHd7nxJHmd"},{"type":"citeGroup","kind":"parenthetical","children":[{"type":"cite","kind":"parenthetical","label":"Hartsuijker2007","identifier":"hartsuijker2007","children":[{"type":"text","value":"Hartsuijker & Welleman, 2007","key":"G7a0qltptr"}],"enumerator":"1","key":"OvLEslddTf"}],"key":"P3CKuVCBjq"},{"type":"text","value":".","position":{"start":{"line":28,"column":1},"end":{"line":28,"column":1}},"key":"Z3ccnwZJDT"}],"key":"TSp0OmvmpG"},{"type":"heading","depth":2,"position":{"start":{"line":30,"column":1},"end":{"line":30,"column":1}},"children":[{"type":"text","value":"Cross-sectional shear stresses","position":{"start":{"line":30,"column":1},"end":{"line":30,"column":1}},"key":"HSibvMPzA4"}],"identifier":"cross-sectional-shear-stresses","label":"Cross-sectional shear stresses","html_id":"cross-sectional-shear-stresses","implicit":true,"key":"ivVXwmLWz4"},{"type":"paragraph","position":{"start":{"line":32,"column":1},"end":{"line":32,"column":1}},"children":[{"type":"text","value":"The shear stress in the cross-sectional direction is givenby:","position":{"start":{"line":32,"column":1},"end":{"line":32,"column":1}},"key":"HZKLGVTdxw"}],"key":"zEIzhDhz7P"},{"type":"math","value":"\\sigma_{xm} = \\frac{s_x^a}{b^a}","position":{"start":{"line":34,"column":1},"end":{"line":34,"column":1}},"html":"<span class=\"katex-display\"><span class=\"katex\"><span class=\"katex-mathml\"><math xmlns=\"http://www.w3.org/1998/Math/MathML\" display=\"block\"><semantics><mrow><msub><mi>σ</mi><mrow><mi>x</mi><mi>m</mi></mrow></msub><mo>=</mo><mfrac><msubsup><mi>s</mi><mi>x</mi><mi>a</mi></msubsup><msup><mi>b</mi><mi>a</mi></msup></mfrac></mrow><annotation encoding=\"application/x-tex\">\\sigma_{xm} = \\frac{s_x^a}{b^a}</annotation></semantics></math></span><span class=\"katex-html\" aria-hidden=\"true\"><span class=\"base\"><span class=\"strut\" style=\"height:0.5806em;vertical-align:-0.15em;\"></span><span class=\"mord\"><span class=\"mord mathnormal\" style=\"margin-right:0.03588em;\">σ</span><span class=\"msupsub\"><span class=\"vlist-t vlist-t2\"><span class=\"vlist-r\"><span class=\"vlist\" style=\"height:0.1514em;\"><span style=\"top:-2.55em;margin-left:-0.0359em;margin-right:0.05em;\"><span class=\"pstrut\" style=\"height:2.7em;\"></span><span class=\"sizing reset-size6 size3 mtight\"><span class=\"mord mtight\"><span class=\"mord mathnormal mtight\">x</span><span class=\"mord mathnormal mtight\">m</span></span></span></span></span><span class=\"vlist-s\">​</span></span><span class=\"vlist-r\"><span class=\"vlist\" style=\"height:0.15em;\"><span></span></span></span></span></span></span><span class=\"mspace\" style=\"margin-right:0.2778em;\"></span><span class=\"mrel\">=</span><span class=\"mspace\" style=\"margin-right:0.2778em;\"></span></span><span class=\"base\"><span class=\"strut\" style=\"height:2.0274em;vertical-align:-0.686em;\"></span><span class=\"mord\"><span class=\"mopen nulldelimiter\"></span><span class=\"mfrac\"><span class=\"vlist-t vlist-t2\"><span class=\"vlist-r\"><span class=\"vlist\" style=\"height:1.3414em;\"><span style=\"top:-2.314em;\"><span class=\"pstrut\" style=\"height:3em;\"></span><span class=\"mord\"><span class=\"mord\"><span class=\"mord mathnormal\">b</span><span class=\"msupsub\"><span class=\"vlist-t\"><span class=\"vlist-r\"><span class=\"vlist\" style=\"height:0.5904em;\"><span style=\"top:-2.989em;margin-right:0.05em;\"><span class=\"pstrut\" style=\"height:2.7em;\"></span><span class=\"sizing reset-size6 size3 mtight\"><span class=\"mord mathnormal mtight\">a</span></span></span></span></span></span></span></span></span></span><span style=\"top:-3.23em;\"><span class=\"pstrut\" style=\"height:3em;\"></span><span class=\"frac-line\" style=\"border-bottom-width:0.04em;\"></span></span><span style=\"top:-3.677em;\"><span class=\"pstrut\" style=\"height:3em;\"></span><span class=\"mord\"><span class=\"mord\"><span class=\"mord mathnormal\">s</span><span class=\"msupsub\"><span class=\"vlist-t vlist-t2\"><span class=\"vlist-r\"><span class=\"vlist\" style=\"height:0.6644em;\"><span style=\"top:-2.453em;margin-left:0em;margin-right:0.05em;\"><span class=\"pstrut\" style=\"height:2.7em;\"></span><span class=\"sizing reset-size6 size3 mtight\"><span class=\"mord mathnormal mtight\">x</span></span></span><span style=\"top:-3.063em;margin-right:0.05em;\"><span class=\"pstrut\" style=\"height:2.7em;\"></span><span class=\"sizing reset-size6 size3 mtight\"><span class=\"mord mathnormal mtight\">a</span></span></span></span><span class=\"vlist-s\">​</span></span><span class=\"vlist-r\"><span class=\"vlist\" style=\"height:0.247em;\"><span></span></span></span></span></span></span></span></span></span><span class=\"vlist-s\">​</span></span><span class=\"vlist-r\"><span class=\"vlist\" style=\"height:0.686em;\"><span></span></span></span></span></span><span class=\"mclose nulldelimiter\"></span></span></span></span></span></span>","enumerator":"4","key":"x694KuV0tl"},{"type":"paragraph","position":{"start":{"line":36,"column":1},"end":{"line":36,"column":1}},"children":[{"type":"text","value":"This is treated in chapter 5.3 and 5.4 of the book Engineering Mechanics Volume 2 ","position":{"start":{"line":36,"column":1},"end":{"line":36,"column":1}},"key":"GkHzjkkpHK"},{"type":"citeGroup","kind":"parenthetical","children":[{"type":"cite","kind":"parenthetical","label":"Hartsuijker2007","identifier":"hartsuijker2007","children":[{"type":"text","value":"Hartsuijker & Welleman, 2007","key":"Q9ejJfWONH"}],"enumerator":"1","key":"pbok87FTsj"}],"key":"JqHY717IPl"},{"type":"text","value":".","position":{"start":{"line":36,"column":1},"end":{"line":36,"column":1}},"key":"il3c2aPXbu"}],"key":"uCClC1coLX"},{"type":"heading","depth":2,"position":{"start":{"line":38,"column":1},"end":{"line":38,"column":1}},"children":[{"type":"text","value":"Exercises","position":{"start":{"line":38,"column":1},"end":{"line":38,"column":1}},"key":"prgKTHgiUy"}],"identifier":"exercises","label":"Exercises","html_id":"exercises","implicit":true,"key":"nOhB1l7amW"},{"type":"list","ordered":false,"spread":false,"position":{"start":{"line":39,"column":1},"end":{"line":40,"column":1}},"children":[{"type":"listItem","spread":true,"position":{"start":{"line":39,"column":1},"end":{"line":39,"column":1}},"children":[{"type":"text","value":"If you’re a TU Delft student, you can practise with the following ","position":{"start":{"line":39,"column":1},"end":{"line":39,"column":1}},"key":"gkE8G2y8vt"},{"type":"link","url":"https://ans.app/digital_test/assignments/1166418/results/new","position":{"start":{"line":39,"column":1},"end":{"line":39,"column":1}},"children":[{"type":"image","url":"/ANS-780378025bf38eab0a7ca67d4765a546.svg","alt":"ANS","key":"PQz8D95Dom","urlSource":"../../images/ANS.svg"},{"type":"text","value":" exercises","position":{"start":{"line":39,"column":1},"end":{"line":39,"column":1}},"key":"PW0QAt8DW5"}],"urlSource":"https://ans.app/digital_test/assignments/1166418/results/new","key":"Qv9fwn4UQ4"}],"key":"w2pQ1LD5Vm"},{"type":"listItem","spread":true,"position":{"start":{"line":40,"column":1},"end":{"line":40,"column":1}},"children":[{"type":"text","value":"Exercises 5.1-5.48, 5.59-5.73, 5.75-5.80 in chapter 5.8 of the book Engineering Mechanics Volume 2 ","position":{"start":{"line":40,"column":1},"end":{"line":40,"column":1}},"key":"lPnsNppKXJ"},{"type":"citeGroup","kind":"parenthetical","children":[{"type":"cite","kind":"parenthetical","label":"Hartsuijker2007","identifier":"hartsuijker2007","children":[{"type":"text","value":"Hartsuijker & Welleman, 2007","key":"GYzRX4HLKk"}],"enumerator":"1","key":"FNXqQJQXZA"}],"key":"UZNf08QmaR"},{"type":"text","value":". Answers are available on ","position":{"start":{"line":40,"column":1},"end":{"line":40,"column":1}},"key":"u3Y33bm8Ad"},{"type":"link","url":"https://icozct.tudelft.nl/TUD_CT/bookanswers/vol2/Chapter5/","position":{"start":{"line":40,"column":1},"end":{"line":40,"column":1}},"children":[{"type":"text","value":"this website","position":{"start":{"line":40,"column":1},"end":{"line":40,"column":1}},"key":"caEug3XpkS"}],"urlSource":"https://icozct.tudelft.nl/TUD_CT/bookanswers/vol2/Chapter5/","key":"CptplPztLB"},{"type":"text","value":".","position":{"start":{"line":40,"column":1},"end":{"line":40,"column":1}},"key":"aXnMUwEb7V"}],"key":"XW5fy2SFQ1"}],"key":"RlYso4JrGX"}],"key":"wVJBHIDqc5"}],"key":"abuy7BoAqN"},"references":{"cite":{"order":["Hartsuijker2007"],"data":{"Hartsuijker2007":{"label":"Hartsuijker2007","enumerator":"1","doi":"10.1007/978-1-4020-5763-2","html":"Hartsuijker, C., & Welleman, J. W. (2007). <i>Engineering Mechanics: Volume 2: Stresses, strains and displacements</i>. Springer Netherlands. <a target=\"_blank\" rel=\"noreferrer\" href=\"https://doi.org/10.1007/978-1-4020-5763-2\">10.1007/978-1-4020-5763-2</a>","url":"https://doi.org/10.1007/978-1-4020-5763-2"}}}}}